djtempl/__init__.py
djtempl/cli.py
djtempl/djtempl.py
djtempl-1.0.1.dist-info/DESCRIPTION.rst
djtempl-1.0.1.dist-info/entry_points.txt
djtempl-1.0.1.dist-info/METADATA
djtempl-1.0.1.dist-info/metadata.json
djtempl-1.0.1.dist-info/RECORD
djtempl-1.0.1.dist-info/top_level.txt
djtempl-1.0.1.dist-info/WHEEL
