Metadata-Version: 2.0
Name: djtempl
Version: 1.0.1
Summary: Generate dockerfiles from pip requirements.txt 
Home-page: https://github.com/emailgregn/djtempl
Author: Greg N
Author-email: emailgregn@gmail.com
License: GPLv3+
Keywords: Docker Django template pip requirements
Platform: UNKNOWN
Classifier: Development Status :: 3 - Alpha
Classifier: Intended Audience :: Developers
Classifier: Topic :: Software Development :: Build Tools
Classifier: License :: OSI Approved :: GNU General Public License v3 or later (GPLv3+)
Classifier: Programming Language :: Python :: 2.7
Requires-Dist: django
Requires-Dist: pip
Provides-Extra: dev
Requires-Dist: check-manifest; extra == 'dev'
Provides-Extra: test
Requires-Dist: coverage; extra == 'test'
